<?xml version="1.0" encoding="UTF-8"?>
<?xml-stylesheet href="bookstore.xsl" type="text/xsl" ?>
<Bookstore>


<Book>

<Title>BookTitle1</Title>
<author>reema theraja</author>
<year>2005</year>
<price>35.00</price>
</Book>

<Book>
<Title>BookTitle2</Title>
<author>reema theraja</author>
<year>2005</year>
<price>35.00</price>
</Book>

<Book>
<Title>BookTitle3</Title>
<author>reema theraja</author>
<year>2005</year>
<price>35.00</price>
</Book>

<Book>
<Title>BookTitle4</Title>
<author>reema theraja</author>
<year>2005</year>
<price>35.00</price>
</Book>

<Book>
<Title>BookTitle5</Title>
<author>reema theraja</author>
<year>2005</year>
<price>35.00</price>
</Book>


</Bookstore>
